[{"using":true,"id_user":"82fe0fdc053d40","_id":"5c93b4b748f54146a306950a","id":"3-V-RER01","__v":0},{"using":false,"id_user":"","_id":"5c93b4b848f54146a306950b","id":"3-V-RER02","__v":0},{"using":false,"id_user":"","_id":"5c93b4b848f54146a306950c","id":"3-V-RER03","__v":0},{"using":false,"id_user":"","_id":"5c93b4b848f54146a306950d","id":"3-V-RER04","__v":0},{"using":false,"id_user":"","_id":"5c93b4b848f54146a306950e","id":"3-V-RER05","__v":0},{"using":false,"id_user":"","_id":"5c93b4b848f54146a306950f","id":"3-V-RER06","__v":0},{"using":false,"id_user":"","_id":"5c93b4b848f54146a3069510","id":"3-V-RER07","__v":0},{"using":false,"id_user":"","_id":"5c93b4b848f54146a3069511","id":"3-V-RER08","__v":0},{"using":false,"id_user":"","_id":"5c93b4b848f54146a3069512","id":"3-V-RER09","__v":0},{"using":false,"id_user":"","_id":"5c93b4b848f54146a3069513","id":"3-V-RER10","__v":0},{"using":false,"id_user":"","_id":"5c93b4b848f54146a3069514","id":"3-V-RER11","__v":0},{"using":false,"id_user":"","_id":"5c93b4b848f54146a3069515","id":"3-V-RER12","__v":0},{"using":false,"id_user":"","_id":"5c93b4b948f54146a3069516","id":"3-V-RER13","__v":0},{"using":false,"id_user":"","_id":"5c93b4b948f54146a3069517","id":"3-V-RER14","__v":0},{"using":false,"id_user":"","_id":"5c93b4b948f54146a3069518","id":"3-V-RER15","__v":0},{"using":false,"id_user":"","_id":"5c93b4b948f54146a3069519","id":"3-V-RER16","__v":0},{"using":false,"id_user":"","_id":"5c93b4b948f54146a306951a","id":"3-V-RER17","__v":0},{"using":false,"id_user":"","_id":"5c93b4b948f54146a306951b","id":"3-V-RER18","__v":0},{"using":false,"id_user":"","_id":"5c93b4b948f54146a306951c","id":"3-V-RER19","__v":0},{"using":false,"id_user":"","_id":"5c93b4b948f54146a306951d","id":"3-V-RER20","__v":0},{"using":false,"id_user":"","_id":"5c93b4b948f54146a306951e","id":"3-V-RER21","__v":0},{"using":false,"id_user":"","_id":"5c93b4b948f54146a306951f","id":"3-V-RER22","__v":0},{"using":false,"id_user":"","_id":"5c93b4b948f54146a3069520","id":"3-V-MILIEU01","__v":0},{"using":false,"id_user":"","_id":"5c93b4b948f54146a3069521","id":"3-V-MILIEU02","__v":0},{"using":false,"id_user":"","_id":"5c93b4b948f54146a3069522","id":"3-V-MILIEU03","__v":0},{"using":false,"id_user":"","_id":"5c93b4b948f54146a3069523","id":"3-V-MILIEU04","__v":0},{"using":false,"id_user":"","_id":"5c93b4b948f54146a3069524","id":"3-V-MILIEU05","__v":0},{"using":false,"id_user":"","_id":"5c93b4b948f54146a3069525","id":"3-V-MILIEU06","__v":0},{"using":false,"id_user":"","_id":"5c93b4b948f54146a3069526","id":"3-V-MILIEU07","__v":0},{"using":false,"id_user":"","_id":"5c93b4b948f54146a3069527","id":"3-V-MILIEU08","__v":0},{"using":false,"id_user":"","_id":"5c93b4b948f54146a3069528","id":"3-V-MILIEU09","__v":0},{"using":false,"id_user":"","_id":"5c93b4b948f54146a3069529","id":"3-V-MILIEU10","__v":0},{"using":false,"id_user":"","_id":"5c93b4b948f54146a306952a","id":"3-V-MILIEU11","__v":0},{"using":false,"id_user":"","_id":"5c93b4b948f54146a306952b","id":"3-V-MILIEU12","__v":0},{"using":false,"id_user":"","_id":"5c93b4ba48f54146a306952c","id":"3-V-MILIEU13","__v":0},{"using":false,"id_user":"","_id":"5c93b4ba48f54146a306952d","id":"3-V-MILIEU14","__v":0},{"using":false,"id_user":"","_id":"5c93b4ba48f54146a306952e","id":"3-V-MILIEU15","__v":0},{"using":false,"id_user":"","_id":"5c93b4ba48f54146a306952f","id":"3-V-BOIS01","__v":0},{"using":false,"id_user":"","_id":"5c93b4ba48f54146a3069530","id":"3-V-BOIS02","__v":0},{"using":false,"id_user":"","_id":"5c93b4ba48f54146a3069531","id":"3-V-BOIS03","__v":0},{"using":false,"id_user":"","_id":"5c93b4ba48f54146a3069532","id":"3-V-BOIS04","__v":0},{"using":false,"id_user":"","_id":"5c93b4ba48f54146a3069533","id":"3-V-BOIS05","__v":0},{"using":false,"id_user":"","_id":"5c93b4ba48f54146a3069534","id":"3-V-BOIS06","__v":0},{"using":false,"id_user":"","_id":"5c93b4ba48f54146a3069535","id":"3-V-BOIS07","__v":0},{"using":false,"id_user":"","_id":"5c93b4ba48f54146a3069536","id":"3-V-BOIS08","__v":0},{"using":false,"id_user":"","_id":"5c93b4ba48f54146a3069537","id":"3-V-BOIS09","__v":0},{"using":false,"id_user":"","_id":"5c93b4ba48f54146a3069538","id":"3-V-BOIS10","__v":0},{"using":false,"id_user":"","_id":"5c93b4ba48f54146a3069539","id":"3-V-BOIS11","__v":0},{"using":false,"id_user":"","_id":"5c93b4ba48f54146a306953a","id":"3-V-BOIS12","__v":0},{"using":false,"id_user":"","_id":"5c93b4ba48f54146a306953b","id":"3-V-BOIS13","__v":0},{"using":false,"id_user":"","_id":"5c93b4ba48f54146a306953c","id":"3-V-BOIS14","__v":0},{"using":false,"id_user":"","_id":"5c93b4ba48f54146a306953d","id":"3-V-BOIS15","__v":0},{"using":false,"id_user":"","_id":"5c93b4ba48f54146a306953e","id":"3-V-BOIS16","__v":0},{"using":false,"id_user":"","_id":"5c93b4ba48f54146a306953f","id":"3-B-RER01","__v":0},{"using":false,"id_user":"","_id":"5c93b4ba48f54146a3069540","id":"3-B-RER02","__v":0},{"using":false,"id_user":"","_id":"5c93b4ba48f54146a3069541","id":"3-B-RER03","__v":0},{"using":false,"id_user":"","_id":"5c93b4bb48f54146a3069542","id":"3-B-RER04","__v":0},{"using":false,"id_user":"","_id":"5c93b4bb48f54146a3069543","id":"3-B-RER05","__v":0},{"using":false,"id_user":"","_id":"5c93b4bb48f54146a3069544","id":"3-B-RER06","__v":0},{"using":false,"id_user":"","_id":"5c93b4bb48f54146a3069545","id":"3-B-RER07","__v":0},{"using":false,"id_user":"","_id":"5c93b4bb48f54146a3069546","id":"3-B-RER08","__v":0},{"using":false,"id_user":"","_id":"5c93b4bb48f54146a3069547","id":"3-B-RER09","__v":0},{"using":false,"id_user":"","_id":"5c93b4bb48f54146a3069548","id":"3-B-RER10","__v":0},{"using":false,"id_user":"","_id":"5c93b4bb48f54146a3069549","id":"3-B-RER11","__v":0},{"using":false,"id_user":"","_id":"5c93b4bb48f54146a306954a","id":"3-B-RER12","__v":0},{"using":false,"id_user":"","_id":"5c93b4bb48f54146a306954b","id":"3-B-RER13","__v":0},{"using":false,"id_user":"","_id":"5c93b4bb48f54146a306954c","id":"3-B-RER14","__v":0},{"using":false,"id_user":"","_id":"5c93b4bb48f54146a306954d","id":"3-B-RER15","__v":0},{"using":false,"id_user":"","_id":"5c93b4bb48f54146a306954e","id":"3-B-RER16","__v":0},{"using":false,"id_user":"","_id":"5c93b4bb48f54146a306954f","id":"3-B-RER17","__v":0},{"using":false,"id_user":"","_id":"5c93b4bb48f54146a3069550","id":"3-B-RER18","__v":0},{"using":false,"id_user":"","_id":"5c93b4bb48f54146a3069551","id":"3-B-RER19","__v":0},{"using":false,"id_user":"","_id":"5c93b4bb48f54146a3069552","id":"3-B-RER20","__v":0},{"using":false,"id_user":"","_id":"5c93b4bb48f54146a3069553","id":"3-B-RER21","__v":0},{"using":false,"id_user":"","_id":"5c93b4bb48f54146a3069554","id":"3-B-RER22","__v":0},{"using":false,"id_user":"","_id":"5c93b4bb48f54146a3069555","id":"3-B-RER23","__v":0},{"using":false,"id_user":"","_id":"5c93b4bb48f54146a3069556","id":"3-B-RER24","__v":0},{"using":false,"id_user":"","_id":"5c93b4bb48f54146a3069557","id":"3-B-RER25","__v":0},{"using":false,"id_user":"","_id":"5c93b4bc48f54146a3069558","id":"3-B-RER26","__v":0},{"using":false,"id_user":"","_id":"5c93b4bc48f54146a3069559","id":"3-B-RER27","__v":0},{"using":false,"id_user":"","_id":"5c93b4bc48f54146a306955a","id":"3-B-RER28","__v":0},{"using":false,"id_user":"","_id":"5c93b4bc48f54146a306955b","id":"3-B-RER29","__v":0},{"using":false,"id_user":"","_id":"5c93b4bc48f54146a306955c","id":"3-B-RER30","__v":0},{"using":false,"id_user":"","_id":"5c93b4bc48f54146a306955d","id":"3-B-RER31","__v":0},{"using":false,"id_user":"","_id":"5c93b4bc48f54146a306955e","id":"3-B-RER32","__v":0},{"using":false,"id_user":"","_id":"5c93b4bc48f54146a306955f","id":"3-B-RER33","__v":0},{"using":false,"id_user":"","_id":"5c93b4bc48f54146a3069560","id":"3-B-RER34","__v":0},{"using":false,"id_user":"","_id":"5c93b4bc48f54146a3069561","id":"3-B-MILIEU01","__v":0},{"using":false,"id_user":"","_id":"5c93b4bc48f54146a3069562","id":"3-B-MILIEU02","__v":0},{"using":false,"id_user":"","_id":"5c93b4bc48f54146a3069563","id":"3-B-MILIEU03","__v":0},{"using":false,"id_user":"","_id":"5c93b4bc48f54146a3069564","id":"3-B-MILIEU04","__v":0},{"using":false,"id_user":"","_id":"5c93b4bc48f54146a3069565","id":"3-B-MILIEU05","__v":0},{"using":false,"id_user":"","_id":"5c93b4bc48f54146a3069566","id":"3-B-BOIS01","__v":0},{"using":false,"id_user":"","_id":"5c93b4bc48f54146a3069567","id":"3-B-BOIS02","__v":0},{"using":false,"id_user":"","_id":"5c93b4bc48f54146a3069568","id":"3-B-BOIS03","__v":0},{"using":false,"id_user":"","_id":"5c93b4bc48f54146a3069569","id":"3-B-BOIS04","__v":0},{"using":false,"id_user":"","_id":"5c93b4bc48f54146a306956a","id":"3-B-BOIS05","__v":0},{"using":false,"id_user":"","_id":"5c93b4bc48f54146a306956b","id":"3-B-BOIS06","__v":0},{"using":false,"id_user":"","_id":"5c93b4bc48f54146a306956c","id":"3-B-BOIS07","__v":0},{"using":false,"id_user":"","_id":"5c93b4bd48f54146a306956d","id":"3-B-BOIS08","__v":0},{"using":false,"id_user":"","_id":"5c93b4bd48f54146a306956e","id":"3-B-BOIS09","__v":0},{"using":false,"id_user":"","_id":"5c93b4bd48f54146a306956f","id":"3-B-BOIS10","__v":0},{"using":false,"id_user":"","_id":"5c93b4bd48f54146a3069570","id":"3-B-BOIS11","__v":0},{"using":false,"id_user":"","_id":"5c93b4bd48f54146a3069571","id":"3-B-BOIS12","__v":0},{"using":false,"id_user":"","_id":"5c93b4bd48f54146a3069572","id":"3-B-BOIS13","__v":0},{"using":false,"id_user":"","_id":"5c93b4bd48f54146a3069573","id":"3-B-BOIS14","__v":0},{"using":false,"id_user":"","_id":"5c93b4bd48f54146a3069574","id":"3-B-BOIS15","__v":0},{"using":false,"id_user":"","_id":"5c93b4bd48f54146a3069575","id":"3-B-BOIS16","__v":0},{"using":false,"id_user":"","_id":"5c93b4bd48f54146a3069576","id":"3-B-BOIS17","__v":0},{"using":false,"id_user":"","_id":"5c93b4bd48f54146a3069577","id":"3-B-BOIS18","__v":0},{"using":false,"id_user":"","_id":"5c93b4bd48f54146a3069578","id":"3-B-BOIS19","__v":0},{"using":false,"id_user":"","_id":"5c93b4bd48f54146a3069579","id":"3-B-BOIS20","__v":0},{"using":false,"id_user":"","_id":"5c93b4bd48f54146a306957a","id":"3-B-BOIS21","__v":0},{"using":false,"id_user":"","_id":"5c93b4bd48f54146a306957b","id":"3-B-BOIS22","__v":0},{"using":false,"id_user":"","_id":"5c93b4bd48f54146a306957c","id":"3-B-BOIS23","__v":0},{"using":false,"id_user":"","_id":"5c93b4bd48f54146a306957d","id":"3-B-BOIS24","__v":0},{"using":false,"id_user":"","_id":"5c93b4bd48f54146a306957e","id":"3-B-BOIS25","__v":0},{"using":false,"id_user":"","_id":"5c93b4bd48f54146a306957f","id":"3-B-BOIS26","__v":0},{"using":false,"id_user":"","_id":"5c93b4bd48f54146a3069580","id":"3-B-BOIS27","__v":0},{"using":false,"id_user":"","_id":"5c93b4bd48f54146a3069581","id":"3-B-BOIS28","__v":0},{"using":false,"id_user":"","_id":"5c93b4bd48f54146a3069582","id":"3-B-BOIS29","__v":0},{"using":false,"id_user":"","_id":"5c93b4be48f54146a3069583","id":"3-B-BOIS30","__v":0},{"using":false,"id_user":"","_id":"5c93b4be48f54146a3069584","id":"3-B-BOIS31","__v":0},{"using":false,"id_user":"","_id":"5c93b4be48f54146a3069585","id":"3-B-BOIS32","__v":0},{"using":false,"id_user":"","_id":"5c93b4be48f54146a3069586","id":"3-R-MILIEU01","__v":0},{"using":false,"id_user":"","_id":"5c93b4be48f54146a3069587","id":"3-R-MILIEU02","__v":0},{"using":false,"id_user":"","_id":"5c93b4be48f54146a3069588","id":"3-R-MILIEU03","__v":0},{"using":false,"id_user":"","_id":"5c93b4be48f54146a3069589","id":"3-R-MILIEU04","__v":0},{"using":false,"id_user":"","_id":"5c93b4be48f54146a306958a","id":"3-R-MILIEU05","__v":0},{"using":false,"id_user":"","_id":"5c93b4be48f54146a306958b","id":"3-R-MILIEU06","__v":0},{"using":false,"id_user":"","_id":"5c93b4be48f54146a306958c","id":"3-R-MILIEU07","__v":0},{"using":false,"id_user":"","_id":"5c93b4be48f54146a306958d","id":"3-R-MILIEU08","__v":0},{"using":false,"id_user":"","_id":"5c93b4be48f54146a306958e","id":"3-R-MILIEU09","__v":0},{"using":false,"id_user":"","_id":"5c93b4be48f54146a306958f","id":"3-R-BOIS01","__v":0},{"using":false,"id_user":"","_id":"5c93b4be48f54146a3069590","id":"3-R-BOIS02","__v":0},{"using":false,"id_user":"","_id":"5c93b4be48f54146a3069591","id":"3-R-BOIS03","__v":0},{"using":false,"id_user":"","_id":"5c93b4be48f54146a3069592","id":"3-R-BOIS04","__v":0},{"using":false,"id_user":"","_id":"5c93b4be48f54146a3069593","id":"3-R-BOIS05","__v":0},{"using":false,"id_user":"","_id":"5c93b4be48f54146a3069594","id":"3-R-BOIS06","__v":0},{"using":false,"id_user":"","_id":"5c93b4be48f54146a3069595","id":"3-R-BOIS07","__v":0},{"using":false,"id_user":"","_id":"5c93b4be48f54146a3069596","id":"3-R-BOIS08","__v":0},{"using":false,"id_user":"","_id":"5c93b4bf48f54146a3069597","id":"3-R-BOIS09","__v":0},{"using":false,"id_user":"","_id":"5c93b4bf48f54146a3069598","id":"3-R-BOIS10","__v":0},{"using":false,"id_user":"","_id":"5c93b4bf48f54146a3069599","id":"3-R-BOIS11","__v":0},{"using":false,"id_user":"","_id":"5c93b4bf48f54146a306959a","id":"3-R-BOIS12","__v":0},{"using":false,"id_user":"","_id":"5c93b4bf48f54146a306959b","id":"3-R-BOIS13","__v":0},{"using":false,"id_user":"","_id":"5c93b4bf48f54146a306959c","id":"3-R-BOIS14","__v":0},{"using":false,"id_user":"","_id":"5c93b4bf48f54146a306959d","id":"3-R-BOIS15","__v":0},{"using":false,"id_user":"","_id":"5c93b4bf48f54146a306959e","id":"3-R-BOIS16","__v":0},{"using":false,"id_user":"","_id":"5c93b4bf48f54146a306959f","id":"3-R-BOIS17","__v":0},{"using":false,"id_user":"","_id":"5c93b4bf48f54146a30695a0","id":"3-R-BOIS18","__v":0},{"using":false,"id_user":"","_id":"5c93b4bf48f54146a30695a1","id":"3-R-BOIS19","__v":0},{"using":false,"id_user":"","_id":"5c93b4bf48f54146a30695a2","id":"3-R-BOIS20","__v":0},{"using":false,"id_user":"","_id":"5c93b4bf48f54146a30695a3","id":"3-R-BOIS21","__v":0},{"using":false,"id_user":"","_id":"5c93b4bf48f54146a30695a4","id":"3-R-BOIS22","__v":0},{"using":false,"id_user":"","_id":"5c93b4bf48f54146a30695a5","id":"3-R-BOIS23","__v":0},{"using":false,"id_user":"","_id":"5c93b4bf48f54146a30695a6","id":"4-V-RER01","__v":0},{"using":false,"id_user":"","_id":"5c93b4bf48f54146a30695a7","id":"4-V-RER02","__v":0},{"using":false,"id_user":"","_id":"5c93b4bf48f54146a30695a8","id":"4-V-RER03","__v":0},{"using":false,"id_user":"","_id":"5c93b4bf48f54146a30695a9","id":"4-V-RER04","__v":0},{"using":false,"id_user":"","_id":"5c93b4bf48f54146a30695aa","id":"4-V-RER05","__v":0},{"using":false,"id_user":"","_id":"5c93b4bf48f54146a30695ab","id":"4-V-RER06","__v":0},{"using":false,"id_user":"","_id":"5c93b4bf48f54146a30695ac","id":"4-V-RER07","__v":0},{"using":false,"id_user":"","_id":"5c93b4c048f54146a30695ad","id":"4-V-RER08","__v":0},{"using":false,"id_user":"","_id":"5c93b4c048f54146a30695ae","id":"4-V-RER09","__v":0},{"using":false,"id_user":"","_id":"5c93b4c048f54146a30695af","id":"4-V-RER10","__v":0},{"using":false,"id_user":"","_id":"5c93b4c048f54146a30695b0","id":"4-V-RER11","__v":0},{"using":false,"id_user":"","_id":"5c93b4c048f54146a30695b1","id":"4-V-RER12","__v":0},{"using":false,"id_user":"","_id":"5c93b4c048f54146a30695b2","id":"4-V-RER13","__v":0},{"using":false,"id_user":"","_id":"5c93b4c048f54146a30695b3","id":"4-V-RER14","__v":0},{"using":false,"id_user":"","_id":"5c93b4c048f54146a30695b4","id":"4-V-RER15","__v":0},{"using":false,"id_user":"","_id":"5c93b4c048f54146a30695b5","id":"4-V-RER16","__v":0},{"using":false,"id_user":"","_id":"5c93b4c048f54146a30695b6","id":"4-V-RER17","__v":0},{"using":false,"id_user":"","_id":"5c93b4c048f54146a30695b7","id":"4-V-RER18","__v":0},{"using":false,"id_user":"","_id":"5c93b4c048f54146a30695b8","id":"4-V-RER19","__v":0},{"using":false,"id_user":"","_id":"5c93b4c048f54146a30695b9","id":"4-V-MILIEU01","__v":0},{"using":false,"id_user":"","_id":"5c93b4c048f54146a30695ba","id":"4-V-MILIEU02","__v":0},{"using":false,"id_user":"","_id":"5c93b4c048f54146a30695bb","id":"4-V-MILIEU03","__v":0},{"using":false,"id_user":"","_id":"5c93b4c048f54146a30695bc","id":"4-V-MILIEU04","__v":0},{"using":false,"id_user":"","_id":"5c93b4c048f54146a30695bd","id":"4-V-MILIEU05","__v":0},{"using":false,"id_user":"","_id":"5c93b4c048f54146a30695be","id":"4-V-MILIEU06","__v":0},{"using":false,"id_user":"","_id":"5c93b4c048f54146a30695bf","id":"4-V-MILIEU07","__v":0},{"using":false,"id_user":"","_id":"5c93b4c048f54146a30695c0","id":"4-V-MILIEU08","__v":0},{"using":false,"id_user":"","_id":"5c93b4c048f54146a30695c1","id":"4-V-MILIEU09","__v":0},{"using":false,"id_user":"","_id":"5c93b4c048f54146a30695c2","id":"4-V-MILIEU10","__v":0},{"using":false,"id_user":"","_id":"5c93b4c148f54146a30695c3","id":"4-V-BOIS01","__v":0},{"using":false,"id_user":"","_id":"5c93b4c148f54146a30695c4","id":"4-V-BOIS02","__v":0},{"using":false,"id_user":"","_id":"5c93b4c148f54146a30695c5","id":"4-V-BOIS03","__v":0},{"using":false,"id_user":"","_id":"5c93b4c148f54146a30695c6","id":"4-V-BOIS04","__v":0},{"using":false,"id_user":"","_id":"5c93b4c148f54146a30695c7","id":"4-V-BOIS05","__v":0},{"using":false,"id_user":"","_id":"5c93b4c148f54146a30695c8","id":"4-V-BOIS06","__v":0},{"using":false,"id_user":"","_id":"5c93b4c148f54146a30695c9","id":"4-V-BOIS07","__v":0},{"using":false,"id_user":"","_id":"5c93b4c148f54146a30695ca","id":"4-V-BOIS08","__v":0},{"using":false,"id_user":"","_id":"5c93b4c148f54146a30695cb","id":"4-V-BOIS09","__v":0},{"using":false,"id_user":"","_id":"5c93b4c148f54146a30695cc","id":"4-V-BOIS10","__v":0},{"using":false,"id_user":"","_id":"5c93b4c148f54146a30695cd","id":"4-V-BOIS11","__v":0},{"using":false,"id_user":"","_id":"5c93b4c148f54146a30695ce","id":"4-V-BOIS12","__v":0},{"using":false,"id_user":"","_id":"5c93b4c148f54146a30695cf","id":"4-V-BOIS13","__v":0},{"using":false,"id_user":"","_id":"5c93b4c148f54146a30695d0","id":"4-V-BOIS14","__v":0},{"using":false,"id_user":"","_id":"5c93b4c148f54146a30695d1","id":"4-V-BOIS15","__v":0},{"using":false,"id_user":"","_id":"5c93b4c148f54146a30695d2","id":"4-V-BOIS16","__v":0},{"using":false,"id_user":"","_id":"5c93b4c148f54146a30695d3","id":"4-V-BOIS17","__v":0},{"using":false,"id_user":"","_id":"5c93b4c148f54146a30695d4","id":"4-V-BOIS18","__v":0},{"using":false,"id_user":"","_id":"5c93b4c148f54146a30695d5","id":"4-V-BOIS19","__v":0},{"using":false,"id_user":"","_id":"5c93b4c148f54146a30695d6","id":"4-V-BOIS20","__v":0},{"using":false,"id_user":"","_id":"5c93b4c148f54146a30695d7","id":"4-V-BOIS21","__v":0},{"using":false,"id_user":"","_id":"5c93b4c148f54146a30695d8","id":"4-V-BOIS22","__v":0},{"using":false,"id_user":"","_id":"5c93b4c248f54146a30695d9","id":"4-B-RER01","__v":0},{"using":false,"id_user":"","_id":"5c93b4c248f54146a30695da","id":"4-B-RER02","__v":0},{"using":false,"id_user":"","_id":"5c93b4c248f54146a30695db","id":"4-B-RER03","__v":0},{"using":false,"id_user":"","_id":"5c93b4c248f54146a30695dc","id":"4-B-RER04","__v":0},{"using":false,"id_user":"","_id":"5c93b4c248f54146a30695dd","id":"4-B-RER05","__v":0},{"using":false,"id_user":"","_id":"5c93b4c248f54146a30695de","id":"4-B-RER06","__v":0},{"using":false,"id_user":"","_id":"5c93b4c248f54146a30695df","id":"4-B-RER07","__v":0},{"using":false,"id_user":"","_id":"5c93b4c248f54146a30695e0","id":"4-B-RER08","__v":0},{"using":false,"id_user":"","_id":"5c93b4c248f54146a30695e1","id":"4-B-RER09","__v":0},{"using":false,"id_user":"","_id":"5c93b4c248f54146a30695e2","id":"4-B-RER10","__v":0},{"using":false,"id_user":"","_id":"5c93b4c248f54146a30695e3","id":"4-B-RER11","__v":0},{"using":false,"id_user":"","_id":"5c93b4c248f54146a30695e4","id":"4-B-RER12","__v":0},{"using":false,"id_user":"","_id":"5c93b4c248f54146a30695e5","id":"4-B-RER13","__v":0},{"using":false,"id_user":"","_id":"5c93b4c248f54146a30695e6","id":"4-B-RER14","__v":0},{"using":false,"id_user":"","_id":"5c93b4c248f54146a30695e7","id":"4-B-RER15","__v":0},{"using":false,"id_user":"","_id":"5c93b4c348f54146a30695e8","id":"4-B-RER16","__v":0},{"using":false,"id_user":"","_id":"5c93b4c348f54146a30695e9","id":"4-B-RER17","__v":0},{"using":false,"id_user":"","_id":"5c93b4c348f54146a30695ea","id":"4-B-RER18","__v":0},{"using":false,"id_user":"","_id":"5c93b4c348f54146a30695eb","id":"4-B-RER19","__v":0},{"using":false,"id_user":"","_id":"5c93b4c348f54146a30695ec","id":"4-B-RER20","__v":0},{"using":false,"id_user":"","_id":"5c93b4c348f54146a30695ed","id":"4-B-RER21","__v":0},{"using":false,"id_user":"","_id":"5c93b4c348f54146a30695ee","id":"4-B-RER22","__v":0},{"using":false,"id_user":"","_id":"5c93b4c348f54146a30695ef","id":"4-B-RER23","__v":0},{"using":false,"id_user":"","_id":"5c93b4c348f54146a30695f0","id":"4-B-RER24","__v":0},{"using":false,"id_user":"","_id":"5c93b4c348f54146a30695f1","id":"4-B-RER25","__v":0},{"using":false,"id_user":"","_id":"5c93b4c348f54146a30695f2","id":"4-B-RER26","__v":0},{"using":false,"id_user":"","_id":"5c93b4c348f54146a30695f3","id":"4-B-RER27","__v":0},{"using":false,"id_user":"","_id":"5c93b4c348f54146a30695f4","id":"4-B-RER28","__v":0},{"using":false,"id_user":"","_id":"5c93b4c348f54146a30695f5","id":"4-B-RER29","__v":0},{"using":false,"id_user":"","_id":"5c93b4c348f54146a30695f6","id":"4-B-MILIEU01","__v":0},{"using":false,"id_user":"","_id":"5c93b4c348f54146a30695f7","id":"4-B-MILIEU02","__v":0},{"using":false,"id_user":"","_id":"5c93b4c348f54146a30695f8","id":"4-B-MILIEU03","__v":0},{"using":false,"id_user":"","_id":"5c93b4c348f54146a30695f9","id":"4-B-MILIEU04","__v":0},{"using":false,"id_user":"","_id":"5c93b4c348f54146a30695fa","id":"4-B-MILIEU05","__v":0},{"using":false,"id_user":"","_id":"5c93b4c348f54146a30695fb","id":"4-B-MILIEU06","__v":0},{"using":false,"id_user":"","_id":"5c93b4c348f54146a30695fc","id":"4-B-MILIEU07","__v":0},{"using":false,"id_user":"","_id":"5c93b4c448f54146a30695fd","id":"4-B-MILIEU08","__v":0},{"using":false,"id_user":"","_id":"5c93b4c448f54146a30695fe","id":"4-B-MILIEU09","__v":0},{"using":false,"id_user":"","_id":"5c93b4c448f54146a30695ff","id":"4-B-BOIS01","__v":0},{"using":false,"id_user":"","_id":"5c93b4c448f54146a3069600","id":"4-B-BOIS02","__v":0},{"using":false,"id_user":"","_id":"5c93b4c448f54146a3069601","id":"4-B-BOIS03","__v":0},{"using":false,"id_user":"","_id":"5c93b4c448f54146a3069602","id":"4-B-BOIS04","__v":0},{"using":false,"id_user":"","_id":"5c93b4c448f54146a3069603","id":"4-B-BOIS05","__v":0},{"using":false,"id_user":"","_id":"5c93b4c448f54146a3069604","id":"4-B-BOIS06","__v":0},{"using":false,"id_user":"","_id":"5c93b4c448f54146a3069605","id":"4-B-BOIS07","__v":0},{"using":false,"id_user":"","_id":"5c93b4c448f54146a3069606","id":"4-B-BOIS08","__v":0},{"using":false,"id_user":"","_id":"5c93b4c448f54146a3069607","id":"4-B-BOIS09","__v":0},{"using":false,"id_user":"","_id":"5c93b4c448f54146a3069608","id":"4-B-BOIS10","__v":0},{"using":false,"id_user":"","_id":"5c93b4c448f54146a3069609","id":"4-B-BOIS11","__v":0},{"using":false,"id_user":"","_id":"5c93b4c448f54146a306960a","id":"4-B-BOIS12","__v":0},{"using":false,"id_user":"","_id":"5c93b4c448f54146a306960b","id":"4-B-BOIS13","__v":0},{"using":false,"id_user":"","_id":"5c93b4c448f54146a306960c","id":"4-B-BOIS14","__v":0},{"using":false,"id_user":"","_id":"5c93b4c448f54146a306960d","id":"4-B-BOIS15","__v":0},{"using":false,"id_user":"","_id":"5c93b4c448f54146a306960e","id":"4-B-BOIS16","__v":0},{"using":false,"id_user":"","_id":"5c93b4c448f54146a306960f","id":"4-B-BOIS17","__v":0},{"using":false,"id_user":"","_id":"5c93b4c448f54146a3069610","id":"4-B-BOIS18","__v":0},{"using":false,"id_user":"","_id":"5c93b4c448f54146a3069611","id":"4-B-BOIS19","__v":0},{"using":false,"id_user":"","_id":"5c93b4c548f54146a3069612","id":"4-B-BOIS20","__v":0},{"using":false,"id_user":"","_id":"5c93b4c548f54146a3069613","id":"4-B-BOIS21","__v":0},{"using":false,"id_user":"","_id":"5c93b4c548f54146a3069614","id":"4-B-BOIS22","__v":0},{"using":false,"id_user":"","_id":"5c93b4c548f54146a3069615","id":"4-B-BOIS23","__v":0},{"using":false,"id_user":"","_id":"5c93b4c548f54146a3069616","id":"4-B-BOIS24","__v":0},{"using":false,"id_user":"","_id":"5c93b4c548f54146a3069617","id":"4-B-BOIS25","__v":0},{"using":false,"id_user":"","_id":"5c93b4c548f54146a3069618","id":"4-B-BOIS26","__v":0},{"using":false,"id_user":"","_id":"5c93b4c548f54146a3069619","id":"4-B-BOIS27","__v":0},{"using":false,"id_user":"","_id":"5c93b4c548f54146a306961a","id":"4-B-BOIS28","__v":0},{"using":false,"id_user":"","_id":"5c93b4c548f54146a306961b","id":"4-B-BOIS29","__v":0},{"using":false,"id_user":"","_id":"5c93b4c548f54146a306961c","id":"4-B-BOIS30","__v":0},{"using":false,"id_user":"","_id":"5c93b4c548f54146a306961d","id":"4-B-BOIS31","__v":0},{"using":false,"id_user":"","_id":"5c93b4c548f54146a306961e","id":"4-B-BOIS32","__v":0},{"using":false,"id_user":"","_id":"5c93b4c548f54146a306961f","id":"4-B-BOIS33","__v":0},{"using":false,"id_user":"","_id":"5c93b4c548f54146a3069620","id":"4-B-BOIS34","__v":0},{"using":false,"id_user":"","_id":"5c93b4c548f54146a3069621","id":"4-B-BOIS35","__v":0},{"using":false,"id_user":"","_id":"5c93b4c548f54146a3069622","id":"4-B-BOIS36","__v":0},{"using":false,"id_user":"","_id":"5c93b4c548f54146a3069623","id":"4-B-BOIS37","__v":0},{"using":false,"id_user":"","_id":"5c93b4c548f54146a3069624","id":"4-R-RER01","__v":0},{"using":false,"id_user":"","_id":"5c93b4c648f54146a3069625","id":"4-R-RER02","__v":0},{"using":false,"id_user":"","_id":"5c93b4c648f54146a3069626","id":"4-R-RER03","__v":0},{"using":false,"id_user":"","_id":"5c93b4c648f54146a3069627","id":"4-R-RER04","__v":0},{"using":false,"id_user":"","_id":"5c93b4c648f54146a3069628","id":"4-R-RER05","__v":0},{"using":false,"id_user":"","_id":"5c93b4c648f54146a3069629","id":"4-R-RER06","__v":0},{"using":false,"id_user":"","_id":"5c93b4c648f54146a306962a","id":"4-R-RER07","__v":0},{"using":false,"id_user":"","_id":"5c93b4c648f54146a306962b","id":"4-R-RER08","__v":0},{"using":false,"id_user":"","_id":"5c93b4c648f54146a306962c","id":"4-R-RER09","__v":0},{"using":false,"id_user":"","_id":"5c93b4c648f54146a306962d","id":"4-R-RER10","__v":0},{"using":false,"id_user":"","_id":"5c93b4c648f54146a306962e","id":"4-R-RER11","__v":0},{"using":false,"id_user":"","_id":"5c93b4c648f54146a306962f","id":"4-R-RER12","__v":0},{"using":false,"id_user":"","_id":"5c93b4c648f54146a3069630","id":"4-R-RER13","__v":0},{"using":false,"id_user":"","_id":"5c93b4c648f54146a3069631","id":"4-R-RER14","__v":0},{"using":false,"id_user":"","_id":"5c93b4c648f54146a3069632","id":"4-R-RER15","__v":0},{"using":false,"id_user":"","_id":"5c93b4c648f54146a3069633","id":"4-R-RER16","__v":0},{"using":false,"id_user":"","_id":"5c93b4c648f54146a3069634","id":"4-R-RER17","__v":0},{"using":false,"id_user":"","_id":"5c93b4c648f54146a3069635","id":"4-R-RER18","__v":0},{"using":false,"id_user":"","_id":"5c93b4c748f54146a3069636","id":"4-R-RER19","__v":0},{"using":false,"id_user":"","_id":"5c93b4c748f54146a3069637","id":"4-R-RER20","__v":0},{"using":false,"id_user":"","_id":"5c93b4c748f54146a3069638","id":"4-R-RER21","__v":0},{"using":false,"id_user":"","_id":"5c93b4c748f54146a3069639","id":"4-R-RER22","__v":0},{"using":false,"id_user":"","_id":"5c93b4c748f54146a306963a","id":"4-R-RER23","__v":0},{"using":false,"id_user":"","_id":"5c93b4c748f54146a306963b","id":"4-R-RER24","__v":0},{"using":false,"id_user":"","_id":"5c93b4c748f54146a306963c","id":"4-R-RER25","__v":0},{"using":false,"id_user":"","_id":"5c93b4c748f54146a306963d","id":"4-R-RER26","__v":0},{"using":false,"id_user":"","_id":"5c93b4c748f54146a306963e","id":"4-R-RER27","__v":0},{"using":false,"id_user":"","_id":"5c93b4c748f54146a306963f","id":"4-R-RER28","__v":0},{"using":false,"id_user":"","_id":"5c93b4c748f54146a3069640","id":"4-R-RER29","__v":0},{"using":false,"id_user":"","_id":"5c93b4c748f54146a3069641","id":"4-R-RER30","__v":0},{"using":false,"id_user":"","_id":"5c93b4c748f54146a3069642","id":"4-R-RER31","__v":0},{"using":false,"id_user":"","_id":"5c93b4c748f54146a3069643","id":"4-R-RER32","__v":0},{"using":false,"id_user":"","_id":"5c93b4c748f54146a3069644","id":"4-R-RER33","__v":0},{"using":false,"id_user":"","_id":"5c93b4c748f54146a3069645","id":"4-R-RER34","__v":0},{"using":false,"id_user":"","_id":"5c93b4c748f54146a3069646","id":"4-R-MILIEU01","__v":0},{"using":false,"id_user":"","_id":"5c93b4c748f54146a3069647","id":"4-R-MILIEU02","__v":0},{"using":false,"id_user":"","_id":"5c93b4c748f54146a3069648","id":"4-R-MILIEU03","__v":0},{"using":false,"id_user":"","_id":"5c93b4c748f54146a3069649","id":"4-R-MILIEU04","__v":0},{"using":false,"id_user":"","_id":"5c93b4c748f54146a306964a","id":"4-R-BOIS01","__v":0},{"using":false,"id_user":"","_id":"5c93b4c848f54146a306964b","id":"4-R-BOIS02","__v":0},{"using":false,"id_user":"","_id":"5c93b4c848f54146a306964c","id":"4-R-BOIS03","__v":0},{"using":false,"id_user":"","_id":"5c93b4c848f54146a306964d","id":"4-R-BOIS04","__v":0},{"using":false,"id_user":"","_id":"5c93b4c848f54146a306964e","id":"4-R-BOIS05","__v":0},{"using":false,"id_user":"","_id":"5c93b4c848f54146a306964f","id":"4-R-BOIS06","__v":0},{"using":false,"id_user":"","_id":"5c93b4c848f54146a3069650","id":"4-R-BOIS07","__v":0},{"using":false,"id_user":"","_id":"5c93b4c848f54146a3069651","id":"4-R-BOIS08","__v":0},{"using":false,"id_user":"","_id":"5c93b4c848f54146a3069652","id":"4-R-BOIS09","__v":0},{"using":false,"id_user":"","_id":"5c93b4c848f54146a3069653","id":"4-R-BOIS10","__v":0},{"using":false,"id_user":"","_id":"5c93b4c848f54146a3069654","id":"4-R-BOIS11","__v":0},{"using":false,"id_user":"","_id":"5c93b4c848f54146a3069655","id":"4-R-BOIS12","__v":0},{"using":false,"id_user":"","_id":"5c93b4c848f54146a3069656","id":"4-R-BOIS13","__v":0},{"using":false,"id_user":"","_id":"5c93b4c848f54146a3069657","id":"4-R-BOIS14","__v":0},{"using":false,"id_user":"","_id":"5c93b4c848f54146a3069658","id":"4-R-BOIS15","__v":0},{"using":false,"id_user":"","_id":"5c93b4c848f54146a3069659","id":"4-R-BOIS16","__v":0},{"using":false,"id_user":"","_id":"5c93b4c848f54146a306965a","id":"4-R-BOIS17","__v":0},{"using":false,"id_user":"","_id":"5c93b4c848f54146a306965b","id":"4-R-BOIS18","__v":0},{"using":false,"id_user":"","_id":"5c93b4c848f54146a306965c","id":"4-R-BOIS19","__v":0},{"using":false,"id_user":"","_id":"5c93b4c848f54146a306965d","id":"4-R-BOIS20","__v":0},{"using":false,"id_user":"","_id":"5c93b4c848f54146a306965e","id":"4-R-BOIS21","__v":0},{"using":false,"id_user":"","_id":"5c93b4c948f54146a306965f","id":"4-R-BOIS22","__v":0},{"using":false,"id_user":"","_id":"5c93b4c948f54146a3069660","id":"4-R-BOIS23","__v":0},{"using":false,"id_user":"","_id":"5c93b4c948f54146a3069661","id":"4-R-BOIS24","__v":0},{"using":false,"id_user":"","_id":"5c93b4c948f54146a3069662","id":"4-R-BOIS25","__v":0},{"using":false,"id_user":"","_id":"5c93b4c948f54146a3069663","id":"4-R-BOIS26","__v":0},{"using":false,"id_user":"","_id":"5c93b4c948f54146a3069664","id":"4-R-BOIS27","__v":0},{"using":false,"id_user":"","_id":"5c93b4c948f54146a3069665","id":"4-R-BOIS28","__v":0},{"using":false,"id_user":"","_id":"5c93b4c948f54146a3069666","id":"4-R-BOIS29","__v":0},{"using":false,"id_user":"","_id":"5c93b4c948f54146a3069667","id":"4-R-BOIS30","__v":0},{"using":false,"id_user":"","_id":"5c93b4c948f54146a3069668","id":"4-R-BOIS31","__v":0},{"using":false,"id_user":"","_id":"5c93b4c948f54146a3069669","id":"4-R-BOIS32","__v":0},{"using":false,"id_user":"","_id":"5c93b4c948f54146a306966a","id":"4-R-BOIS33","__v":0},{"using":false,"id_user":"","_id":"5c93b4c948f54146a306966b","id":"4-R-BOIS34","__v":0},{"using":false,"id_user":"","_id":"5c93b4c948f54146a306966c","id":"4-R-BOIS35","__v":0},{"using":false,"id_user":"","_id":"5c93b4c948f54146a306966d","id":"4-R-BOIS36","__v":0},{"using":false,"id_user":"","_id":"5c93b4c948f54146a306966e","id":"4-R-BOIS37","__v":0},{"using":false,"id_user":"","_id":"5c93b4c948f54146a306966f","id":"4-R-BOIS38","__v":0},{"using":false,"id_user":"","_id":"5c93b4c948f54146a3069670","id":"4-R-BOIS39","__v":0},{"using":false,"id_user":"","_id":"5c93b4c948f54146a3069671","id":"4-R-BOIS40","__v":0},{"using":false,"id_user":"","_id":"5c93b4ca48f54146a3069672","id":"4-R-BOIS41","__v":0},{"using":false,"id_user":"","_id":"5c93b4ca48f54146a3069673","id":"4-R-BOIS42","__v":0},{"using":false,"id_user":"","_id":"5c93b4ca48f54146a3069674","id":"4-R-BOIS43","__v":0},{"using":false,"id_user":"","_id":"5c93b4ca48f54146a3069675","id":"4-R-BOIS44","__v":0},{"using":false,"id_user":"","_id":"5c93b4ca48f54146a3069676","id":"4-R-BOIS45","__v":0},{"using":false,"id_user":"","_id":"5c93b5415a0a58473b671952","id":"3-V-RER23","__v":0},{"using":false,"id_user":"","_id":"5c93b5425a0a58473b671962","id":"3-V-MILIEU16","__v":0},{"using":false,"id_user":"","_id":"5c93b5435a0a58473b671973","id":"3-V-BOIS17","__v":0},{"using":false,"id_user":"","_id":"5c93b5455a0a58473b671996","id":"3-B-RER35","__v":0},{"using":false,"id_user":"","_id":"5c93b5455a0a58473b67199c","id":"3-B-MILIEU06","__v":0},{"using":false,"id_user":"","_id":"5c93b5475a0a58473b6719bd","id":"3-B-BOIS33","__v":0},{"using":false,"id_user":"","_id":"5c93b5475a0a58473b6719c7","id":"3-R-MILIEU10","__v":0},{"using":false,"id_user":"","_id":"5c93b5485a0a58473b6719df","id":"3-R-BOIS24","__v":0},{"using":false,"id_user":"","_id":"5c93b5495a0a58473b6719f3","id":"4-V-RER20","__v":0},{"using":false,"id_user":"","_id":"5c93b54a5a0a58473b6719fe","id":"4-V-MILIEU11","__v":0},{"using":false,"id_user":"","_id":"5c93b54b5a0a58473b671a15","id":"4-V-BOIS23","__v":0},{"using":false,"id_user":"","_id":"5c93b54d5a0a58473b671a33","id":"4-B-RER30","__v":0},{"using":false,"id_user":"","_id":"5c93b54d5a0a58473b671a3d","id":"4-B-MILIEU10","__v":0},{"using":false,"id_user":"","_id":"5c93b54f5a0a58473b671a63","id":"4-B-BOIS38","__v":0},{"using":false,"id_user":"","_id":"5c93b5515a0a58473b671a86","id":"4-R-RER35","__v":0},{"using":false,"id_user":"","_id":"5c93b5515a0a58473b671a8b","id":"4-R-MILIEU05","__v":0},{"using":false,"id_user":"","_id":"5c93b5535a0a58473b671ab9","id":"4-R-BOIS46","__v":0},{"using":false,"id_user":"","_id":"5c9e25643a6d1c339a0749e9","id":"3-V-RER24","__v":0},{"using":false,"id_user":"","_id":"5c9e25643a6d1c339a0749ea","id":"3-V-RER25","__v":0},{"using":false,"id_user":"","_id":"5c9e25643a6d1c339a0749eb","id":"3-V-RER26","__v":0},{"using":false,"id_user":"","_id":"5c9e25653a6d1c339a0749fc","id":"3-V-MILIEU17","__v":0},{"using":false,"id_user":"","_id":"5c9e25663a6d1c339a074a0e","id":"3-V-BOIS18","__v":0},{"using":false,"id_user":"","_id":"5c9e25663a6d1c339a074a0f","id":"3-V-BOIS19","__v":0},{"using":false,"id_user":"","_id":"5c9e25663a6d1c339a074a10","id":"3-V-BOIS20","__v":0},{"using":false,"id_user":"","_id":"5c9e25663a6d1c339a074a11","id":"3-V-BOIS21","__v":0},{"using":false,"id_user":"","_id":"5c9e25663a6d1c339a074a12","id":"3-V-BOIS22","__v":0},{"using":false,"id_user":"","_id":"5c9e256a3a6d1c339a074a56","id":"3-B-BOIS34","__v":0},{"using":false,"id_user":"","_id":"5c9e256a3a6d1c339a074a57","id":"3-B-BOIS35","__v":0},{"using":false,"id_user":"","_id":"5c9e256a3a6d1c339a074a58","id":"3-B-BOIS36","__v":0},{"using":false,"id_user":"","_id":"5c9e256a3a6d1c339a074a59","id":"3-B-BOIS37","__v":0},{"using":false,"id_user":"","_id":"5c9e256a3a6d1c339a074a5a","id":"3-B-BOIS38","__v":0},{"using":false,"id_user":"","_id":"5c9e256a3a6d1c339a074a5b","id":"3-B-BOIS39","__v":0},{"using":false,"id_user":"","_id":"5c9e256a3a6d1c339a074a5c","id":"3-B-BOIS40","__v":0},{"using":false,"id_user":"","_id":"5c9e256a3a6d1c339a074a5d","id":"3-B-BOIS41","__v":0},{"using":false,"id_user":"","_id":"5c9e256a3a6d1c339a074a5e","id":"3-B-BOIS42","__v":0},{"using":false,"id_user":"","_id":"5c9e256a3a6d1c339a074a5f","id":"3-B-BOIS43","__v":0},{"using":false,"id_user":"","_id":"5c9e256a3a6d1c339a074a60","id":"3-R-RER01","__v":0},{"using":false,"id_user":"","_id":"5c9e256a3a6d1c339a074a61","id":"3-R-RER02","__v":0},{"using":false,"id_user":"","_id":"5c9e256a3a6d1c339a074a62","id":"3-R-RER03","__v":0},{"using":false,"id_user":"","_id":"5c9e256a3a6d1c339a074a63","id":"3-R-RER04","__v":0},{"using":false,"id_user":"","_id":"5c9e256a3a6d1c339a074a64","id":"3-R-RER05","__v":0},{"using":false,"id_user":"","_id":"5c9e256a3a6d1c339a074a65","id":"3-R-RER06","__v":0},{"using":false,"id_user":"","_id":"5c9e256a3a6d1c339a074a66","id":"3-R-RER07","__v":0},{"using":false,"id_user":"","_id":"5c9e256b3a6d1c339a074a67","id":"3-R-RER08","__v":0},{"using":false,"id_user":"","_id":"5c9e256b3a6d1c339a074a68","id":"3-R-RER09","__v":0},{"using":false,"id_user":"","_id":"5c9e256b3a6d1c339a074a69","id":"3-R-RER10","__v":0},{"using":false,"id_user":"","_id":"5c9e256b3a6d1c339a074a6a","id":"3-R-RER11","__v":0},{"using":false,"id_user":"","_id":"5c9e256b3a6d1c339a074a6b","id":"3-R-RER12","__v":0},{"using":false,"id_user":"","_id":"5c9e256b3a6d1c339a074a6c","id":"3-R-RER13","__v":0},{"using":false,"id_user":"","_id":"5c9e256b3a6d1c339a074a6d","id":"3-R-RER14","__v":0},{"using":false,"id_user":"","_id":"5c9e256b3a6d1c339a074a6e","id":"3-R-RER15","__v":0},{"using":false,"id_user":"","_id":"5c9e256b3a6d1c339a074a6f","id":"3-R-RER16","__v":0},{"using":false,"id_user":"","_id":"5c9e256b3a6d1c339a074a70","id":"3-R-RER17","__v":0},{"using":false,"id_user":"","_id":"5c9e256b3a6d1c339a074a71","id":"3-R-RER18","__v":0},{"using":false,"id_user":"","_id":"5c9e256b3a6d1c339a074a72","id":"3-R-RER19","__v":0},{"using":false,"id_user":"","_id":"5c9e256b3a6d1c339a074a73","id":"3-R-RER20","__v":0},{"using":false,"id_user":"","_id":"5c9e256b3a6d1c339a074a74","id":"3-R-RER21","__v":0},{"using":false,"id_user":"","_id":"5c9e256b3a6d1c339a074a75","id":"3-R-RER22","__v":0},{"using":false,"id_user":"","_id":"5c9e256b3a6d1c339a074a76","id":"3-R-RER23","__v":0},{"using":false,"id_user":"","_id":"5c9e256b3a6d1c339a074a77","id":"3-R-RER24","__v":0},{"using":false,"id_user":"","_id":"5c9e256b3a6d1c339a074a78","id":"3-R-RER25","__v":0},{"using":false,"id_user":"","_id":"5c9e256b3a6d1c339a074a79","id":"3-R-RER26","__v":0},{"using":false,"id_user":"","_id":"5c9e256c3a6d1c339a074a7a","id":"3-R-RER27","__v":0},{"using":false,"id_user":"","_id":"5c9e256c3a6d1c339a074a7b","id":"3-R-RER28","__v":0},{"using":false,"id_user":"","_id":"5c9e256c3a6d1c339a074a7c","id":"3-R-RER29","__v":0},{"using":false,"id_user":"","_id":"5c9e256c3a6d1c339a074a7d","id":"3-R-RER30","__v":0},{"using":false,"id_user":"","_id":"5c9e256c3a6d1c339a074a7e","id":"3-R-RER31","__v":0},{"using":false,"id_user":"","_id":"5c9e256c3a6d1c339a074a7f","id":"3-R-RER32","__v":0},{"using":false,"id_user":"","_id":"5c9e256c3a6d1c339a074a80","id":"3-R-RER33","__v":0},{"using":false,"id_user":"","_id":"5c9e256c3a6d1c339a074a81","id":"3-R-RER34","__v":0},{"using":false,"id_user":"","_id":"5c9e256c3a6d1c339a074a82","id":"3-R-RER35","__v":0},{"using":false,"id_user":"","_id":"5c9e256c3a6d1c339a074a83","id":"3-R-RER36","__v":0},{"using":false,"id_user":"","_id":"5c9e256d3a6d1c339a074a8e","id":"3-R-MILIEU11","__v":0},{"using":false,"id_user":"","_id":"5c9e256d3a6d1c339a074a8f","id":"3-R-MILIEU12","__v":0},{"using":false,"id_user":"","_id":"5c9e256d3a6d1c339a074a90","id":"3-R-MILIEU13","__v":0},{"using":false,"id_user":"","_id":"5c9e256e3a6d1c339a074aa9","id":"3-R-BOIS25","__v":0},{"using":false,"id_user":"","_id":"5c9e256f3a6d1c339a074aaa","id":"3-R-BOIS26","__v":0},{"using":false,"id_user":"","_id":"5c9e256f3a6d1c339a074aab","id":"3-R-BOIS27","__v":0},{"using":false,"id_user":"","_id":"5c9e256f3a6d1c339a074aac","id":"3-R-BOIS28","__v":0},{"using":false,"id_user":"","_id":"5c9e256f3a6d1c339a074aad","id":"3-R-BOIS29","__v":0},{"using":false,"id_user":"","_id":"5c9e256f3a6d1c339a074aae","id":"3-R-BOIS30","__v":0},{"using":false,"id_user":"","_id":"5c9e256f3a6d1c339a074aaf","id":"3-R-BOIS31","__v":0},{"using":false,"id_user":"","_id":"5c9e256f3a6d1c339a074ab0","id":"3-R-BOIS32","__v":0},{"using":false,"id_user":"","_id":"5c9e256f3a6d1c339a074ab1","id":"3-R-BOIS33","__v":0},{"using":false,"id_user":"","_id":"5c9e256f3a6d1c339a074ab2","id":"3-R-BOIS34","__v":0},{"using":false,"id_user":"","_id":"5c9e256f3a6d1c339a074ab3","id":"3-R-BOIS35","__v":0},{"using":false,"id_user":"","_id":"5c9e256f3a6d1c339a074ab4","id":"3-R-BOIS36","__v":0},{"using":false,"id_user":"","_id":"5c9e256f3a6d1c339a074ab5","id":"3-R-BOIS37","__v":0},{"using":false,"id_user":"","_id":"5c9e256f3a6d1c339a074ab6","id":"3-R-BOIS38","__v":0},{"using":false,"id_user":"","_id":"5c9e256f3a6d1c339a074ab7","id":"3-R-BOIS39","__v":0},{"using":false,"id_user":"","_id":"5c9e256f3a6d1c339a074ab8","id":"3-R-BOIS40","__v":0},{"using":false,"id_user":"","_id":"5c9e256f3a6d1c339a074ab9","id":"3-R-BOIS41","__v":0},{"using":false,"id_user":"","_id":"5c9e256f3a6d1c339a074aba","id":"3-R-BOIS42","__v":0},{"using":false,"id_user":"","_id":"5c9e256f3a6d1c339a074abb","id":"3-R-BOIS43","__v":0},{"using":false,"id_user":"","_id":"5c9e256f3a6d1c339a074abc","id":"3-R-BOIS44","__v":0},{"using":false,"id_user":"","_id":"5c9e25703a6d1c339a074abd","id":"3-R-BOIS45","__v":0},{"using":false,"id_user":"","_id":"5c9e25703a6d1c339a074abe","id":"3-R-BOIS46","__v":0},{"using":false,"id_user":"","_id":"5c9e25703a6d1c339a074abf","id":"3-R-BOIS47","__v":0},{"using":false,"id_user":"","_id":"5c9e25703a6d1c339a074ac0","id":"3-R-BOIS48","__v":0},{"using":false,"id_user":"","_id":"5c9e25703a6d1c339a074ac1","id":"3-R-BOIS49","__v":0},{"using":false,"id_user":"","_id":"5c9e25703a6d1c339a074ac2","id":"3-R-BOIS50","__v":0},{"using":false,"id_user":"","_id":"5c9e25703a6d1c339a074ac3","id":"3-R-BOIS51","__v":0},{"using":false,"id_user":"","_id":"5c9e25703a6d1c339a074ac4","id":"3-R-BOIS52","__v":0},{"using":false,"id_user":"","_id":"5c9e25703a6d1c339a074ac5","id":"3-R-BOIS53","__v":0},{"using":false,"id_user":"","_id":"5c9e25703a6d1c339a074ac6","id":"3-R-BOIS54","__v":0},{"using":false,"id_user":"","_id":"5c9e25703a6d1c339a074ac7","id":"3-R-BOIS55","__v":0},{"using":false,"id_user":"","_id":"5c9e25703a6d1c339a074ac8","id":"3-R-BOIS56","__v":0},{"using":false,"id_user":"","_id":"5c9e25713a6d1c339a074add","id":"4-V-RER21","__v":0},{"using":false,"id_user":"","_id":"5c9e25713a6d1c339a074ade","id":"4-V-RER22","__v":0},{"using":false,"id_user":"","_id":"5c9e25713a6d1c339a074adf","id":"4-V-RER23","__v":0},{"using":false,"id_user":"","_id":"5c9e25723a6d1c339a074aeb","id":"4-V-MILIEU12","__v":0},{"using":false,"id_user":"","_id":"5c9e25723a6d1c339a074aec","id":"4-V-MILIEU13","__v":0},{"using":false,"id_user":"","_id":"5c9e25753a6d1c339a074b22","id":"4-B-RER31","__v":0},{"using":false,"id_user":"","_id":"5c9e25753a6d1c339a074b23","id":"4-B-RER32","__v":0},{"using":false,"id_user":"","_id":"5c9e25753a6d1c339a074b24","id":"4-B-RER33","__v":0},{"using":false,"id_user":"","_id":"5c9e25753a6d1c339a074b25","id":"4-B-RER34","__v":0},{"using":false,"id_user":"","_id":"5c9e25753a6d1c339a074b26","id":"4-B-RER35","__v":0},{"using":false,"id_user":"","_id":"5c9e25753a6d1c339a074b27","id":"4-B-RER36","__v":0},{"using":false,"id_user":"","_id":"5c9e25753a6d1c339a074b28","id":"4-B-RER37","__v":0},{"using":false,"id_user":"","_id":"5c9e25753a6d1c339a074b29","id":"4-B-RER38","__v":0},{"using":false,"id_user":"","_id":"5c9e25753a6d1c339a074b2a","id":"4-B-RER39","__v":0},{"using":false,"id_user":"","_id":"5c9e25753a6d1c339a074b2b","id":"4-B-RER40","__v":0},{"using":false,"id_user":"","_id":"5c9e25793a6d1c339a074b72","id":"4-R-RER36","__v":0},{"using":false,"id_user":"","_id":"5c9e25793a6d1c339a074b73","id":"4-R-RER37","__v":0},{"using":false,"id_user":"","_id":"5c9e257a3a6d1c339a074b74","id":"4-R-RER38","__v":0},{"using":false,"id_user":"","_id":"5c9e257a3a6d1c339a074b75","id":"4-R-RER39","__v":0},{"using":false,"id_user":"","_id":"5c9e257a3a6d1c339a074b76","id":"4-R-RER40","__v":0},{"using":false,"id_user":"","_id":"5c9e257a3a6d1c339a074b77","id":"4-R-RER41","__v":0},{"using":false,"id_user":"","_id":"5c9e257a3a6d1c339a074b78","id":"4-R-RER42","__v":0},{"using":false,"id_user":"","_id":"5c9e257a3a6d1c339a074b79","id":"4-R-RER43","__v":0},{"using":false,"id_user":"","_id":"5c9e257a3a6d1c339a074b7a","id":"4-R-RER44","__v":0},{"using":false,"id_user":"","_id":"5c9e257c3a6d1c339a074ba9","id":"4-R-BOIS47","__v":0},{"using":false,"id_user":"","_id":"5c9e257d3a6d1c339a074baa","id":"4-R-BOIS48","__v":0},{"using":false,"id_user":"","_id":"5c9e257d3a6d1c339a074bab","id":"4-R-BOIS49","__v":0},{"using":false,"id_user":"","_id":"5c9e257d3a6d1c339a074bac","id":"4-R-BOIS50","__v":0},{"using":false,"id_user":"","_id":"5c9e257d3a6d1c339a074bad","id":"4-R-BOIS51","__v":0},{"using":false,"id_user":"","_id":"5c9e257d3a6d1c339a074bae","id":"4-R-BOIS52","__v":0},{"using":false,"id_user":"","_id":"5c9e257d3a6d1c339a074baf","id":"4-R-BOIS53","__v":0},{"using":false,"id_user":"","_id":"5c9e257d3a6d1c339a074bb0","id":"4-R-BOIS54","__v":0},{"using":false,"id_user":"","_id":"5c9e257d3a6d1c339a074bb1","id":"4-R-BOIS55","__v":0},{"using":false,"id_user":"","_id":"5c9e257d3a6d1c339a074bb2","id":"4-R-BOIS56","__v":0},{"using":false,"id_user":"","_id":"5c9e257d3a6d1c339a074bb3","id":"4-R-BOIS57","__v":0},{"using":false,"id_user":"","_id":"5c9e257d3a6d1c339a074bb4","id":"4-R-BOIS58","__v":0},{"using":false,"id_user":"","_id":"5c9e257d3a6d1c339a074bb5","id":"4-R-BOIS59","__v":0}]